pr_creator/__init__.py
pr_creator/cli.py
pr_creator/git_urls.py
pr_creator/logging_config.py
pr_creator/state.py
pr_creator/workflow.py
pr_creator/change_agents/__init__.py
pr_creator/change_agents/base.py
pr_creator/change_agents/cursor_agent.py
pr_creator/cursor_utils/__init__.py
pr_creator/cursor_utils/config.py
pr_creator/cursor_utils/runner.py
pr_creator/evaluate_agents/__init__.py
pr_creator/evaluate_agents/base.py
pr_creator/evaluate_agents/cursor_agent.py
pr_creator/naming_agents/__init__.py
pr_creator/naming_agents/base.py
pr_creator/naming_agents/cursor_agent.py
pr_creator/prompt_config/__init__.py
pr_creator/prompt_config/loader.py
pr_creator/repo_discovery/__init__.py
pr_creator/repo_discovery/datadog.py
pr_creator/steps/__init__.py
pr_creator/steps/apply.py
pr_creator/steps/cleanup.py
pr_creator/steps/discover.py
pr_creator/steps/evaluate.py
pr_creator/steps/naming.py
pr_creator/steps/next_repo.py
pr_creator/steps/submit.py
pr_creator/steps/workspace.py
pr_creator/submit_change/__init__.py
pr_creator/submit_change/base.py
pr_creator/submit_change/github_submitter.py
multi_repo_pr_creator-0.1.6.dist-info/METADATA
multi_repo_pr_creator-0.1.6.dist-info/WHEEL
multi_repo_pr_creator-0.1.6.dist-info/entry_points.txt
multi_repo_pr_creator-0.1.6.dist-info/top_level.txt
multi_repo_pr_creator-0.1.6.dist-info/RECORD
