Metadata-Version: 2.4
Name: multi-repo-pr-creator
Version: 0.1.6
Summary: Simple workflow runner that applies change agents and opens PRs.
Author: Leon Patmore
License-Expression: MIT
Project-URL: Homepage, https://github.com/LeonPatmore/pr-creator
Project-URL: Repository, https://github.com/LeonPatmore/pr-creator
Project-URL: Issues, https://github.com/LeonPatmore/pr-creator/issues
Keywords: pull-requests,automation,github,agents
Classifier: Programming Language :: Python :: 3
Classifier: Operating System :: OS Independent
Requires-Python: >=3.9
Requires-Dist: PyGithub
Requires-Dist: pydantic-graph
Requires-Dist: dulwich
Requires-Dist: PyYAML
Requires-Dist: docker
Requires-Dist: datadog-api-client
Provides-Extra: dev
Requires-Dist: pytest; extra == "dev"
Requires-Dist: flake8; extra == "dev"
Requires-Dist: black; extra == "dev"
